gafo/__init__.py
gafo/core.py
gafo-0.1.0.dist-info/licenses/LICENSE
gafo-0.1.0.dist-info/METADATA
gafo-0.1.0.dist-info/WHEEL
gafo-0.1.0.dist-info/top_level.txt
gafo-0.1.0.dist-info/RECORD
