Metadata-Version: 2.4
Name: gafo
Version: 0.1.0
Summary: Simple GAFO file compressor using ZLIB
Author: Your Name
Author-email: Your Name <you@example.com>
License: MIT
Classifier: Programming Language :: Python :: 3
Classifier: License :: OSI Approved :: MIT License
Classifier: Operating System :: OS Independent
Requires-Python: >=3.7
License-File: LICENSE
Dynamic: license-file
